bigquery_funcs/__init__.py
bigquery_funcs/_types.py
bigquery_funcs/auth.py
bigquery_funcs/models.py
bigquery_funcs/queries.py
bigquery_funcs-1.0.3.dist-info/METADATA
bigquery_funcs-1.0.3.dist-info/WHEEL
bigquery_funcs-1.0.3.dist-info/top_level.txt
bigquery_funcs-1.0.3.dist-info/RECORD
