Metadata-Version: 2.2
Name: bigquery_funcs
Version: 1.0.3
Summary: BigQuery functions and/or classes, helper scipts, etc. I commonly use when working with the Python SDK
Requires-Python: >=3.12
Requires-Dist: functag>=1.2.7
Requires-Dist: google-cloud-bigquery>=3.29.0
Requires-Dist: google-cloud-secret-manager>=2.23.0
Requires-Dist: jinja2>=3.1.5
Requires-Dist: python-dotenv>=1.0.1
